FcBus/Message.py
FcBus/ParaOp.py
FcBus/Parameters.py
FcBus/PnuOp.py
FcBus/RecMsg.py
FcBus/SndMsg.py
FcBus/Support.py
FcBus/VltMonitor.py
FcBus/VltOp.py
FcBus/__init__.py
FcBus/boot.py
FcBus/commands.json
FcBus/dbglog.py
FcBus/tmcmds.json
FcBus/tmcmds.py
FcBus/tools.py
FcBus/uitest.py
FcBus/test/e38.py
FcBus/test/release-test.py
FcBus/ymodem/Modem.py
FcBus/ymodem/Protocol.py
FcBus/ymodem/__init__.py
Vlt_Comm-0.1.16.dist-info/LICENSE
Vlt_Comm-0.1.16.dist-info/METADATA
Vlt_Comm-0.1.16.dist-info/WHEEL
Vlt_Comm-0.1.16.dist-info/top_level.txt
Vlt_Comm-0.1.16.dist-info/RECORD
