Metadata-Version: 2.1
Name: Vlt-Comm
Version: 0.1.16
Summary: FcBus library for Vlt drives
Author-email: tangfei <fei.tang@danfoss.com>
License: Copyright (c) 2018 The Python Packaging Authority
Classifier: Programming Language :: Python :: 3
Classifier: License :: OSI Approved :: MIT License
Classifier: Operating System :: OS Independent
Requires-Python: >=3.7
License-File: LICENSE
Requires-Dist: minimalmodbus >=2.0.1
Requires-Dist: pyserial >=3.5
Requires-Dist: pyqtgraph ==0.12.3
Requires-Dist: PySide2 ==5.15.2.1
Requires-Dist: tqdm ==4.64.1
Requires-Dist: icecream ==2.1.3
